gemseo_pseven/__init__.py
gemseo_pseven/lib_pseven.py
gemseo_pseven/pseven_problem_adapter.py
gemseo_pseven/options/PSEVENOPT_options.json
gemseo_pseven-1.0.0.dist-info/CREDITS.rst
gemseo_pseven-1.0.0.dist-info/LICENSE.txt
gemseo_pseven-1.0.0.dist-info/METADATA
gemseo_pseven-1.0.0.dist-info/WHEEL
gemseo_pseven-1.0.0.dist-info/entry_points.txt
gemseo_pseven-1.0.0.dist-info/top_level.txt
gemseo_pseven-1.0.0.dist-info/RECORD
