Metadata-Version: 2.1
Name: gemseo-pseven
Version: 1.0.0
Summary: pSeven wrapper for GEMSEO
Home-page: https://www.irt-saintexupery.com
Author: GEMSEO developers
Author-email: contact@gemseo.org
License: GNU Lesser General Public License v3
Classifier: License :: OSI Approved :: GNU Lesser General Public License v3 (LGPLv3)
Classifier: Intended Audience :: Science/Research
Classifier: Topic :: Scientific/Engineering
Classifier: Operating System :: POSIX :: Linux
Classifier: Operating System :: MacOS
Classifier: Operating System :: Microsoft :: Windows
Classifier: Programming Language :: Python :: 3 :: Only
Classifier: Programming Language :: Python :: 3.8
Classifier: Programming Language :: Python :: 3.9
Classifier: Programming Language :: Python :: 3.10
Requires-Python: <3.11,>=3.8
License-File: LICENSE.txt
License-File: CREDITS.rst
Requires-Dist: gemseo (>=5)
Requires-Dist: numpy
Provides-Extra: test
Requires-Dist: covdefaults ; extra == 'test'
Requires-Dist: pytest ; extra == 'test'
Requires-Dist: pytest-cov ; extra == 'test'
Requires-Dist: pytest-xdist ; extra == 'test'
